planning/__init__.py
planning/app.py
planning/config.py
planning/gantt.py
planning/model.py
planning/data/chart.svg
planning/data/collapse.svg
planning/data/duplicate_task.svg
planning/data/edit.svg
planning/data/expand.svg
planning/data/invalid.svg
planning/data/leave.svg
planning/data/libre-gui-about.svg
planning/data/libre-gui-calendar-leave.svg
planning/data/libre-gui-close.svg
planning/data/libre-gui-contacts.svg
planning/data/libre-gui-expired.svg
planning/data/libre-gui-file.svg
planning/data/libre-gui-folder-open.svg
planning/data/libre-gui-folder.svg
planning/data/libre-gui-help.svg
planning/data/libre-gui-import.svg
planning/data/libre-gui-redo.svg
planning/data/libre-gui-refresh.svg
planning/data/libre-gui-save.svg
planning/data/libre-gui-trash.svg
planning/data/libre-gui-undo.svg
planning/data/logs.svg
planning/data/milestone.svg
planning/data/move_down.svg
planning/data/move_up.svg
planning/data/new_chart.svg
planning/data/new_leave.svg
planning/data/new_milestone.svg
planning/data/new_project.svg
planning/data/new_resource.svg
planning/data/new_task.svg
planning/data/planning-banner.svg
planning/data/planning-title.png
planning/data/planning-title.svg
planning/data/planning.png
planning/data/planning.svg
planning/data/project.svg
planning/data/resource.svg
planning/data/task.svg
planning/data/today.svg
planning/gui/__init__.py
planning/gui/centralwidget.py
planning/gui/logviewer.py
planning/gui/long_text_editor.py
planning/gui/mainwindow.py
planning/gui/multi_selection_combobox.py
planning/gui/svgviewer.py
planning/gui/treewidgets.py
planning/locale/fr/LC_MESSAGES/planning.mo
planning/tests/__init__.py
planning/tests/test_central_widget.py
planning/tests/test_gantt.py
planning/tests/test_logviewer.py
planning/tests/test_model.py
planning/tests/test_svgviewer.py
planning/tests/test_treewidgets.py
planning/tests/test_v1_02.svg
planning/tests/test_v1_03.svg
planning/tests/test_v2_01.svg
planning/tests/test_v2_02.svg
planning/tests/test_v2_03.svg
PyPlanning-2.0.1.dist-info/LICENSE
PyPlanning-2.0.1.dist-info/METADATA
PyPlanning-2.0.1.dist-info/WHEEL
PyPlanning-2.0.1.dist-info/entry_points.txt
PyPlanning-2.0.1.dist-info/top_level.txt
PyPlanning-2.0.1.dist-info/RECORD
