Metadata-Version: 2.1
Name: PyPlanning
Version: 2.0.1
Summary: Manage team schedules and quickly create simple project plannings
Author-email: Pierre Raybaut <p.raybaut@codra.fr>
Maintainer-email: PyPlanning Developers <p.raybaut@codra.fr>
License: GNU GENERAL PUBLIC LICENSE
Project-URL: Homepage, https://github.com/Codra-Ingenierie-Informatique/PyPlanning/
Project-URL: Documentation, https://PyPlanning.readthedocs.io/en/latest/
Classifier: Topic :: Software Development :: Libraries :: Python Modules
Classifier: Topic :: Utilities
Classifier: Topic :: Software Development :: User Interfaces
Classifier: Operating System :: MacOS
Classifier: Operating System :: Microsoft :: Windows
Classifier: Operating System :: OS Independent
Classifier: Operating System :: POSIX
Classifier: Operating System :: Unix
Classifier: Programming Language :: Python :: 3.8
Classifier: Programming Language :: Python :: 3.9
Classifier: Programming Language :: Python :: 3.10
Classifier: Programming Language :: Python :: 3.11
Classifier: Programming Language :: Python :: 3.12
Requires-Python: <4,>=3.8
License-File: LICENSE
Requires-Dist: PyQt5
Requires-Dist: PyQtWebEngine
Requires-Dist: guidata >=3.1
Requires-Dist: svgwrite
Requires-Dist: python-dateutil
Provides-Extra: dev
Requires-Dist: black ; extra == 'dev'
Requires-Dist: isort ; extra == 'dev'
Requires-Dist: pylint ; extra == 'dev'
Requires-Dist: Coverage ; extra == 'dev'
Provides-Extra: doc
Requires-Dist: sphinx >6 ; extra == 'doc'
Requires-Dist: pydata-sphinx-theme ; extra == 'doc'
